dle_encoder/__init__.py
dle_encoder/dle_encoder.py
tests/__init__.py
tests/test_dle_encoder.py
dle_encoder-0.2.3.dist-info/LICENSE
dle_encoder-0.2.3.dist-info/METADATA
dle_encoder-0.2.3.dist-info/NOTICE
dle_encoder-0.2.3.dist-info/WHEEL
dle_encoder-0.2.3.dist-info/top_level.txt
dle_encoder-0.2.3.dist-info/RECORD
