Metadata-Version: 2.1
Name: dle-encoder
Version: 0.2.3
Summary: DLE ASCII Encoder
Home-page: https://github.com/robamu-org/py-dle-encoder
Author: Robin Mueller
Author-email: robin.mueller.m@gmail.com
License: Apache-2.0
Platform: any
Classifier: Development Status :: 5 - Production/Stable
Classifier: License :: OSI Approved :: Apache Software License
Classifier: Natural Language :: English
Classifier: Operating System :: POSIX
Classifier: Operating System :: Microsoft :: Windows
Classifier: Programming Language :: Python :: 3
Classifier: Programming Language :: Python :: 3.7
Classifier: Programming Language :: Python :: 3.8
Classifier: Topic :: Communications
Classifier: Topic :: Software Development :: Libraries
Classifier: Topic :: Software Development :: Libraries :: Python Modules
Classifier: Topic :: Scientific/Engineering
Requires-Python: >=3.7
License-File: LICENSE
License-File: NOTICE
